flask_fomanticui/__init__.py
flask_fomanticui/core.py
flask_fomanticui/fomantic.py
flask_fomanticui/static/css/semantic.css
flask_fomanticui/static/css/semantic.min.css
flask_fomanticui/static/css/themes/basic/assets/fonts/icons.woff
flask_fomanticui/static/css/themes/default/assets/fonts/Lato-Bold.woff
flask_fomanticui/static/css/themes/default/assets/fonts/Lato-Bold.woff2
flask_fomanticui/static/css/themes/default/assets/fonts/Lato-BoldItalic.woff
flask_fomanticui/static/css/themes/default/assets/fonts/Lato-BoldItalic.woff2
flask_fomanticui/static/css/themes/default/assets/fonts/Lato-Italic.woff
flask_fomanticui/static/css/themes/default/assets/fonts/Lato-Italic.woff2
flask_fomanticui/static/css/themes/default/assets/fonts/Lato-Regular.woff
flask_fomanticui/static/css/themes/default/assets/fonts/Lato-Regular.woff2
flask_fomanticui/static/css/themes/default/assets/fonts/LatoLatin-Bold.woff
flask_fomanticui/static/css/themes/default/assets/fonts/LatoLatin-Bold.woff2
flask_fomanticui/static/css/themes/default/assets/fonts/LatoLatin-BoldItalic.woff
flask_fomanticui/static/css/themes/default/assets/fonts/LatoLatin-BoldItalic.woff2
flask_fomanticui/static/css/themes/default/assets/fonts/LatoLatin-Italic.woff
flask_fomanticui/static/css/themes/default/assets/fonts/LatoLatin-Italic.woff2
flask_fomanticui/static/css/themes/default/assets/fonts/LatoLatin-Regular.woff
flask_fomanticui/static/css/themes/default/assets/fonts/LatoLatin-Regular.woff2
flask_fomanticui/static/css/themes/default/assets/fonts/brand-icons.woff
flask_fomanticui/static/css/themes/default/assets/fonts/brand-icons.woff2
flask_fomanticui/static/css/themes/default/assets/fonts/icons.woff
flask_fomanticui/static/css/themes/default/assets/fonts/icons.woff2
flask_fomanticui/static/css/themes/default/assets/fonts/outline-icons.woff
flask_fomanticui/static/css/themes/default/assets/fonts/outline-icons.woff2
flask_fomanticui/static/css/themes/famfamfam/assets/images/flags.png
Flask_FomanticUI-0.0.3.dist-info/LICENSE
Flask_FomanticUI-0.0.3.dist-info/METADATA
Flask_FomanticUI-0.0.3.dist-info/WHEEL
Flask_FomanticUI-0.0.3.dist-info/top_level.txt
Flask_FomanticUI-0.0.3.dist-info/RECORD
